jtep/__init__.py
jtep-0.0.0.dist-info/LICENSE
jtep-0.0.0.dist-info/METADATA
jtep-0.0.0.dist-info/WHEEL
jtep-0.0.0.dist-info/entry_points.txt
jtep-0.0.0.dist-info/top_level.txt
jtep-0.0.0.dist-info/RECORD
