Metadata-Version: 2.1
Name: jtep
Version: 0.0.0
Summary: Command line Jinja template processor
Author-email: Stefan Siegel <ssiegel@sdas.net>
License: GPL-3.0-or-later
Classifier: License :: OSI Approved :: GNU General Public License v3 or later (GPLv3+)
Classifier: Operating System :: OS Independent
Classifier: Programming Language :: Python :: 3
Classifier: Topic :: Text Processing :: General
Classifier: Topic :: Utilities
Requires-Python: >=3.7
License-File: LICENSE
Requires-Dist: click
Requires-Dist: jinja2
Requires-Dist: pyyaml
Requires-Dist: tabulate
Requires-Dist: toml
Requires-Dist: xmltodict
